[
    {"id": 1, "mlb_id": 109, "abbr": "ARI", "hashtag": "DBacks"},
    {"id": 2, "mlb_id": 144, "abbr": "ATL", "hashtag": "Braves"},
    {"id": 3, "mlb_id": 110, "abbr": "BAL", "hashtag": "Orioles"},
    {"id": 4, "mlb_id": 111, "abbr": "BOS", "hashtag": "RedSox"},
    {"id": 5, "mlb_id": 112, "abbr": "CHC", "hashtag": "Cubs"},
    {"id": 6, "mlb_id": 113, "abbr": "CIN", "hashtag": "Reds"},
    {"id": 7, "mlb_id": 114, "abbr": "CLE", "hashtag": "Indians"},
    {"id": 8, "mlb_id": 115, "abbr": "COL", "hashtag": "Rockies"},
    {"id": 9, "mlb_id": 145, "abbr": "CWS", "hashtag": "WhiteSox"},
    {"id": 10, "mlb_id": 116, "abbr": "DET", "hashtag": "Tigers"},
    {"id": 11, "mlb_id": 117, "abbr": "HOU", "hashtag": "Astros"},
    {"id": 12, "mlb_id": 118, "abbr": "KC", "hashtag": "Royals"},
    {"id": 13, "mlb_id": 108, "abbr": "LAA", "hashtag": "Angels"},
    {"id": 14, "mlb_id": 119, "abbr": "LAD", "hashtag": "Dodgers"},
    {"id": 15, "mlb_id": 146, "abbr": "MIA", "hashtag": "Marlins"},
    {"id": 16, "mlb_id": 158, "abbr": "MIL", "hashtag": "Brewers"},
    {"id": 17, "mlb_id": 142, "abbr": "MIN", "hashtag": "Twins"},
    {"id": 18, "mlb_id": 121, "abbr": "NYM", "hashtag": "Mets"},
    {"id": 19, "mlb_id": 147, "abbr": "NYY", "hashtag": "Yankees"},
    {"id": 20, "mlb_id": 133, "abbr": "OAK", "hashtag": "Athletics"},
    {"id": 21, "mlb_id": 143, "abbr": "PHI", "hashtag": "Phillies"},
    {"id": 22, "mlb_id": 134, "abbr": "PIT", "hashtag": "Pirates"},
    {"id": 23, "mlb_id": 135, "abbr": "SD", "hashtag": "Padres"},
    {"id": 24, "mlb_id": 136, "abbr": "SEA", "hashtag": "Mariners"},
    {"id": 25, "mlb_id": 137, "abbr": "SF", "hashtag": "SFGiants"},
    {"id": 26, "mlb_id": 138, "abbr": "STL", "hashtag": "STLCards"},
    {"id": 27, "mlb_id": 139, "abbr": "TB", "hashtag": "Rays"},
    {"id": 28, "mlb_id": 140, "abbr": "TEX", "hashtag": "Rangers"},
    {"id": 29, "mlb_id": 141, "abbr": "TOR", "hashtag": "BlueJays"},
    {"id": 30, "mlb_id": 120, "abbr": "WSH", "hashtag": "Nats"}
]
